PyMultiplex/__init__.py
PyMultiplex/__main__.py
PyMultiplex/Channel/Exceptions.py
PyMultiplex/Channel/Message.py
PyMultiplex/Channel/Socket.py
PyMultiplex/Channel/__init__.py
PyMultiplex/Multiplex/MultiplexClient.py
PyMultiplex/Multiplex/MultiplexServer.py
PyMultiplex/Multiplex/__init__.py
PyMultiplex/Threads/MultiplexClientThread.py
PyMultiplex/Threads/MultiplexServerThread.py
PyMultiplex/Threads/MultiplexThread.py
PyMultiplex/Threads/__init__.py
PyMultiplex/utils/Logger.py
PyMultiplex/utils/__init__.py
PyMultiplex/utils/consts.py
pymultiplex-1.15.dist-info/METADATA
pymultiplex-1.15.dist-info/WHEEL
pymultiplex-1.15.dist-info/entry_points.txt
pymultiplex-1.15.dist-info/top_level.txt
pymultiplex-1.15.dist-info/RECORD
