Metadata-Version: 2.4
Name: PyMultiplex
Version: 1.15
Summary: Transfer data across multiple virtual channels over a single socket connection using multiplexing
Home-page: https://github.com/GefenAltshuler/PyMultiplex
Author: Gaffner
Author-email: gefen102@gmail.com
Classifier: Programming Language :: Python :: 3
Dynamic: author
Dynamic: author-email
Dynamic: classifier
Dynamic: description
Dynamic: description-content-type
Dynamic: home-page
Dynamic: summary
